algo_provider/__init__.py
algo_provider/algo_provider.py
algo_provider/app.py
algo_provider/models/__init__.py
algo_provider/models/algorithm.py
algo_provider/utils/__init__.py
algo_provider/utils/parser.py
tests/__init__.py
tests/my_algorithms.py
algo_provider-1.0.2.dist-info/LICENSE
algo_provider-1.0.2.dist-info/METADATA
algo_provider-1.0.2.dist-info/WHEEL
algo_provider-1.0.2.dist-info/top_level.txt
algo_provider-1.0.2.dist-info/RECORD
