Metadata-Version: 2.1
Name: algo-provider
Version: 1.0.2
Summary: Start your own Algo provider from a Python function, interface it DebiAI or something else
Home-page: https://github.com/debiai/easy-algo-provider
Requires-Python: >=3.7
License-File: LICENSE
Requires-Dist: fastapi==0.115.4
Requires-Dist: uvicorn==0.32.0
Requires-Dist: rich==13.9.4
